epicinsightsapis/__init__.py
epicinsightsapis/api_helper.py
epicinsightsapis/configuration.py
epicinsightsapis/epicinsightsapis_client.py
epicinsightsapis/controllers/__init__.py
epicinsightsapis/controllers/alerta_controller.py
epicinsightsapis/controllers/base_controller.py
epicinsightsapis/controllers/health_controller.py
epicinsightsapis/controllers/tsdb_query_controller.py
epicinsightsapis/exceptions/__init__.py
epicinsightsapis/exceptions/api_exception.py
epicinsightsapis/exceptions/insights_api_v_1_orgs_devices_health_401_error_exception.py
epicinsightsapis/exceptions/insights_api_v_1_orgs_devices_health_403_error_exception.py
epicinsightsapis/exceptions/insights_api_v_1_orgs_devices_health_404_error_exception.py
epicinsightsapis/exceptions/insights_api_v_1_orgs_health_alert_401_error_exception.py
epicinsightsapis/exceptions/insights_api_v_1_orgs_health_alert_403_error_exception.py
epicinsightsapis/exceptions/insights_api_v_1_orgs_health_alert_404_error_exception.py
epicinsightsapis/exceptions/insights_api_v_1_orgs_health_alert_action_401_error_exception.py
epicinsightsapis/exceptions/insights_api_v_1_orgs_health_alert_action_403_error_exception.py
epicinsightsapis/exceptions/insights_api_v_1_orgs_health_alert_action_404_error_exception.py
epicinsightsapis/exceptions/insights_api_v_1_orgs_health_alerts_401_error_exception.py
epicinsightsapis/exceptions/insights_api_v_1_orgs_health_alerts_403_error_exception.py
epicinsightsapis/exceptions/insights_api_v_1_orgs_health_alerts_404_error_exception.py
epicinsightsapis/exceptions/insights_api_v_1_orgs_health_alerts_count_401_error_exception.py
epicinsightsapis/exceptions/insights_api_v_1_orgs_health_alerts_count_403_error_exception.py
epicinsightsapis/exceptions/insights_api_v_1_orgs_health_alerts_count_404_error_exception.py
epicinsightsapis/exceptions/insights_api_v_1_orgs_tsdb_query_401_error_exception.py
epicinsightsapis/exceptions/insights_api_v_1_orgs_tsdb_query_403_error_exception.py
insights1_sdk-1.0.6.dist-info/LICENSE
insights1_sdk-1.0.6.dist-info/METADATA
insights1_sdk-1.0.6.dist-info/WHEEL
insights1_sdk-1.0.6.dist-info/top_level.txt
insights1_sdk-1.0.6.dist-info/RECORD
