Metadata-Version: 2.1
Name: insights1-sdk
Version: 1.0.6
Summary: Insights
Author-email: vinav <vsvinavsancheti@gmail.com>
Project-URL: Documentation, https://www.juniper.net/documentation/product/us/en/paragon-insights/
Requires-Python: >=3.7
License-File: LICENSE
Requires-Dist: apimatic-core >=0.2.15,~=0.2.0
Requires-Dist: apimatic-core-interfaces >=0.1.5,~=0.1.0
Requires-Dist: apimatic-requests-client-adapter >=0.1.6,~=0.1.0
Requires-Dist: jsonschema ~=3.2.0
Provides-Extra: testutils
Requires-Dist: pytest >=7.2.2 ; extra == 'testutils'
